minder/__init__.py
minder/minder.py
minder-0.0.2.dist-info/LICENSE.txt
minder-0.0.2.dist-info/METADATA
minder-0.0.2.dist-info/WHEEL
minder-0.0.2.dist-info/top_level.txt
minder-0.0.2.dist-info/RECORD
