Metadata-Version: 2.1
Name: minder
Version: 0.0.2
Summary: Exception guard capture utility library
Author-email: Louis Maddox <louismmx@gmail.com>
License: MIT
Project-URL: Homepage, https://github.com/lmmx/minder
Project-URL: Repository, https://github.com/lmmx/minder.git
Classifier: Development Status :: 6 - Mature
Classifier: Framework :: Pydantic :: 2
Classifier: Intended Audience :: Developers
Classifier: Programming Language :: Python :: 3.10
Classifier: Programming Language :: Python :: 3.11
Classifier: Programming Language :: Python :: 3.12
Classifier: Topic :: Software Development :: Libraries
Requires-Python: <=3.12,>=3.9
License-File: LICENSE.txt
